raglab/__init__.py
raglab/app.py
raglab/raglab2.py
raglab/util.py
raglab/stores/__init__.py
raglab/stores/simple_stores.py
raglab/stores/stores_util.py
raglab/web_services/__init__.py
raglab/web_services/mockups.py
raglab/web_services/prompt_templates_dde.py
raglab/web_services/store_access.py
raglab-0.1.2.dist-info/LICENSE
raglab-0.1.2.dist-info/METADATA
raglab-0.1.2.dist-info/WHEEL
raglab-0.1.2.dist-info/top_level.txt
raglab-0.1.2.dist-info/RECORD
