Metadata-Version: 2.1
Name: raglab
Version: 0.1.2
Summary: Backend of a system to explore RAG operations
Home-page: https://github.com/addaix/raglab
License: mit
Platform: any
License-File: LICENSE
Requires-Dist: dol
Requires-Dist: config2py
Requires-Dist: i2
Requires-Dist: dill
